adguardhome/__init__.py
adguardhome/adguardhome.py
adguardhome/exceptions.py
adguardhome/filtering.py
adguardhome/parental.py
adguardhome/py.typed
adguardhome/querylog.py
adguardhome/safebrowsing.py
adguardhome/safesearch.py
adguardhome/stats.py
adguardhome/update.py
adguardhome-0.8.0.dist-info/METADATA
adguardhome-0.8.0.dist-info/WHEEL
adguardhome-0.8.0.dist-info/licenses/LICENSE.md
adguardhome-0.8.0.dist-info/RECORD
