Metadata-Version: 2.4
Name: adguardhome
Version: 0.8.0
Summary: Asynchronous Python client for the AdGuard Home API.
License-Expression: MIT
License-File: LICENSE.md
Keywords: adguard home,adguard,api,async,client
Author: Franck Nijhof
Author-email: opensource@frenck.dev
Maintainer: Franck Nijhof
Maintainer-email: opensource@frenck.dev
Requires-Python: >=3.11
Classifier: Development Status :: 4 - Beta
Classifier: Framework :: AsyncIO
Classifier: Intended Audience :: Developers
Classifier: Natural Language :: English
Classifier: Programming Language :: Python :: 3.11
Classifier: Programming Language :: Python :: 3.12
Classifier: Programming Language :: Python :: 3.13
Classifier: Programming Language :: Python :: 3.14
Classifier: Programming Language :: Python :: 3
Classifier: Topic :: Software Development :: Libraries :: Python Modules
Requires-Dist: aiohttp (>=3.0.0)
Requires-Dist: yarl (>=1.6.0)
Project-URL: Bug Tracker, https://github.com/frenck/python-adguardhome/issues
Project-URL: Changelog, https://github.com/frenck/python-adguardhome/releases
Project-URL: Documentation, https://github.com/frenck/python-adguardhome
Project-URL: Homepage, https://github.com/frenck/python-adguardhome
Project-URL: Repository, https://github.com/frenck/python-adguardhome
